apsw.so
apsw_sqleet-3.28.0.post2.dist-info/METADATA
apsw_sqleet-3.28.0.post2.dist-info/WHEEL
apsw_sqleet-3.28.0.post2.dist-info/RECORD
apsw_sqleet-3.28.0.post2.dist-info/top_level.txt
