Metadata-Version: 2.1
Name: apsw-sqleet
Version: 3.28.0.post2
Summary: Another Python SQLite Wrapper + sqleet backend
Home-page: https://github.com/ArgosyLabs/apsw-sqleet/
Author: Roger Binns
Author-email: rogerb@rogerbinns.com
License: OSI Approved ::
Keywords: database,sqlite
Platform: UNKNOWN
Classifier: Development Status :: 5 - Production/Stable
Classifier: Intended Audience :: Developers
Classifier: License :: OSI Approved
Classifier: Operating System :: OS Independent
Classifier: Programming Language :: C
Classifier: Programming Language :: Python :: 2
Classifier: Programming Language :: Python :: 3
Classifier: Topic :: Database :: Front-Ends
